{
  "custom-diegoeis-obsidianotion@@eis-hide-ribbon": false,
  "custom-diegoeis-obsidianotion@@eis-small-font": true,
  "custom-diegoeis-obsidianotion@@eis-showing-scrollbar": false,
  "custom-diegoeis-obsidianotion@@eis-with-icons": true,
  "custom-diegoeis-obsidianotion@@eis-empty-bg": false,
  "custom-diegoeis-simple@@eis-sidebar-dark": true,
  "custom-diegoeis-simple@@font-default": "IBM Plex Sans",
  "custom-diegoeis-simple@@eis-font-type": "eis-font-ibm",
  "minimal-advanced@@hide-settings-desc": true,
  "minimal-style@@base@@dark": "#030303",
  "minimal-style@@ui2@@dark": "#7017FF",
  "minimal-style@@ax1@@dark": "#7017FF"
}